README.rst
setup.cfg
setup.py
tests/__init__.py
tests/samples.py
tests/test_base58.py
tests/test_curve.py
tests/test_format.py
tests/test_transaction.py
tests/test_utils.py
tests/test_wallet.py
tests/utils.py
tests/network/__init__.py
tests/network/test_fees.py
tests/network/test_meta.py
tests/network/test_rates.py
tests/network/test_services.py
ufobit/__init__.py
ufobit/base32.py
ufobit/base58.py
ufobit/cli.py
ufobit/crypto.py
ufobit/curve.py
ufobit/exceptions.py
ufobit/format.py
ufobit/keygen.py
ufobit/transaction.py
ufobit/utils.py
ufobit/wallet.py
ufobit.egg-info/PKG-INFO
ufobit.egg-info/SOURCES.txt
ufobit.egg-info/dependency_links.txt
ufobit.egg-info/entry_points.txt
ufobit.egg-info/requires.txt
ufobit.egg-info/top_level.txt
ufobit/network/__init__.py
ufobit/network/fees.py
ufobit/network/meta.py
ufobit/network/rates.py
ufobit/network/services.py