Metadata-Version: 1.1
Name: ufobit
Version: 0.8.1
Summary: UFO made easy.
Home-page: https://github.com/ofek/bit
Author: Ofek Lev
Author-email: ofekmeister@gmail.com
License: MIT
Download-URL: https://github.com/ofek/bit
Keywords: ufo,bitcoin,cryptocurrency,payments,tools,wallet
Platform: UNKNOWN
Classifier: Development Status :: 4 - Beta
Classifier: Intended Audience :: Developers
Classifier: Intended Audience :: End Users/Desktop
Classifier: License :: OSI Approved :: MIT License
Classifier: Natural Language :: English
Classifier: Operating System :: OS Independent
Classifier: Programming Language :: Python :: 3.5
Classifier: Programming Language :: Python :: 3.6
Classifier: Programming Language :: Python :: Implementation :: CPython
Classifier: Programming Language :: Python :: Implementation :: PyPy
